setup.py
proxify/__init__.py
proxify.egg-info/PKG-INFO
proxify.egg-info/SOURCES.txt
proxify.egg-info/dependency_links.txt
proxify.egg-info/requires.txt
proxify.egg-info/top_level.txt