Metadata-Version: 1.1
Name: proxify
Version: 1.0.2
Summary: Python module to dump usable proxies.
Home-page: https://github.com/UltimateHackers/proxify
Author: Somdev Sangwan
Author-email: s0md3v@gmail.com
License: GNU General Public License v3 (GPLv3)
Download-URL: https://github.com/UltimateHackers/proxify/tarball/master
Keywords: proxify somdev sangwan d3v
Platform: UNKNOWN
Classifier: Development Status :: 5 - Production/Stable
Classifier: Intended Audience :: Developers
Classifier: License :: OSI Approved :: GNU General Public License v3 (GPLv3)
Classifier: Programming Language :: Python :: 2
Classifier: Programming Language :: Python :: 2.6
Classifier: Programming Language :: Python :: 2.7
Classifier: Programming Language :: Python :: 3
Classifier: Programming Language :: Python :: 3.2
Classifier: Programming Language :: Python :: 3.3
Classifier: Programming Language :: Python :: 3.4
